{
	"ultima_actualizacion": "07/04/2024",
	"imagenes":
	[
		{
			"archivo" : "images/carousel/Pironio_Beato.jpg"
		},
		{
			"archivo" : "images/carousel/SanEduardo.jpg"
		},
		{
			"archivo" : "images/carousel/Teresita.jpg"
		},
		{
			"archivo" : "images/carousel/El Buen Pastor.jpg"
		},
		{
			"archivo" : "images/carousel/Jesus en el Monte.jpg"
		}
	],
	"novedades":
	[
		{
			"texto": "* Ver aviso de Misas Abril 2024 en HORARIOS *"
		},
		{
			"texto": "Horarios Abril a Octubre 2024"
		},
		{
			"texto": "Balance Parroquia Marzo 2024"
		},
		{
			"texto": "Homilía 1er Domingo Tiempo de Pascua"
		},
		{
			"texto": "Homilías Triduo Pascual"
		}
	]
}
